mitarspysigproc/__init__.py
mitarspysigproc/_version.py
mitarspysigproc/detectors.py
mitarspysigproc/estimators.py
mitarspysigproc/filtertools.py
mitarspysigproc/pfb.py
mitarspysigproc/coeffs/kaiseranalysis0002.csv
mitarspysigproc/coeffs/kaiseranalysis0004.csv
mitarspysigproc/coeffs/kaiseranalysis0008.csv
mitarspysigproc/coeffs/kaiseranalysis0016.csv
mitarspysigproc/coeffs/kaiseranalysis0032.csv
mitarspysigproc/coeffs/kaiseranalysis0064.csv
mitarspysigproc/coeffs/kaiseranalysis0128.csv
mitarspysigproc/coeffs/kaiseranalysis0256.csv
mitarspysigproc/coeffs/kaiseranalysis0512.csv
mitarspysigproc/coeffs/kaiseranalysis1024.csv
mitarspysigproc/coeffs/kaisersynthesis0004.csv
mitarspysigproc/coeffs/kaisersynthesis0008.csv
mitarspysigproc/coeffs/kaisersynthesis0016.csv
mitarspysigproc/coeffs/kaisersynthesis0032.csv
mitarspysigproc/coeffs/kaisersynthesis0064.csv
mitarspysigproc/coeffs/kaisersynthesis0128.csv
mitarspysigproc/coeffs/kaisersynthesis0256.csv
mitarspysigproc/coeffs/kaisersynthesis0512.csv
mitarspysigproc/coeffs/kaisersynthesis1024.csv
mitarspysigproc-1.0.1.data/scripts/drf_decompose.py
mitarspysigproc-1.0.1.dist-info/METADATA
mitarspysigproc-1.0.1.dist-info/WHEEL
mitarspysigproc-1.0.1.dist-info/top_level.txt
mitarspysigproc-1.0.1.dist-info/RECORD
