Metadata-Version: 2.4
Name: mitarspysigproc
Version: 1.0.1
Summary: Processing and Plotting of 
Home-page: https://github.com/MIT-Adaptive-Radio-Science/sigprocpython
Author: John Swoboda
Requires-Python: >=3.0
Requires-Dist: scipy
Requires-Dist: numpy
Requires-Dist: matplotlib
Requires-Dist: digital_rf
Dynamic: author
Dynamic: home-page
Dynamic: requires-dist
Dynamic: requires-python
Dynamic: summary
